wayz_rlsdk_python/__init__.py
wayz_rlsdk_python/event_handling.py
wayz_rlsdk_python/events.py
wayz_rlsdk_python/frida_script.py
wayz_rlsdk_python/game_objects.py
wayz_rlsdk_python/sdk.py
wayz_rlsdk_python-0.1.1.dist-info/METADATA
wayz_rlsdk_python-0.1.1.dist-info/WHEEL
wayz_rlsdk_python-0.1.1.dist-info/RECORD
